mask/__init__.py
mask/app.py
mask/config.py
mask/ctx.py
mask/globals.py
mask/interceptor.py
mask/local.py
mask/logging.py
mask/macro.py
mask/protos.py
mask/service.py
mask/utils.py
mask/wrappers.py
mask/parse/__init__.py
mask/parse/exception.py
mask/parse/macro.py
mask/parse/regexp.py
mask/parse/request.py
mask/parse/response.py
mask/parse/rules.py
mask/parse/utils.py
mask/parse/filters/__init__.py
mask/parse/filters/base.py
mask/parse/filters/cross/__init__.py
mask/parse/filters/cross/equal_key_filter.py
mask/parse/filters/cross/required_with_filter.py
mask/parse/filters/simple/__init__.py
mask/parse/filters/simple/content_filter.py
mask/parse/filters/simple/default_filter.py
mask/parse/filters/simple/email_filter.py
mask/parse/filters/simple/empty_filter.py
mask/parse/filters/simple/enum_filter.py
mask/parse/filters/simple/equal_filter.py
mask/parse/filters/simple/file_filter.py
mask/parse/filters/simple/json_filter.py
mask/parse/filters/simple/length_filter.py
mask/parse/filters/simple/location_filter.py
mask/parse/filters/simple/mobile_filter.py
mask/parse/filters/simple/multi_filter.py
mask/parse/filters/simple/network_filter.py
mask/parse/filters/simple/range_filter.py
mask/parse/filters/simple/regexp_filter.py
mask/parse/filters/simple/split_filter.py
mask/parse/filters/simple/string_filter.py
mask/parse/filters/simple/trim_filter.py
mask/parse/filters/simple/type_filter.py
Mask-1.0.0a1.dist-info/METADATA
Mask-1.0.0a1.dist-info/WHEEL
Mask-1.0.0a1.dist-info/top_level.txt
Mask-1.0.0a1.dist-info/RECORD
