Metadata-Version: 2.1
Name: Mask
Version: 1.0.0a1
Summary: A simple gRPC server just like Flask.
Home-page: https://github.com/Eastwu5788/Mask
Author: Wu Dong
Author-email: wudong@eastwu.cn
License: MIT
Project-URL: Document, https://github.com/Eastwu5788/Mask
Project-URL: Source Code, https://github.com/Eastwu5788/Mask
Project-URL: Issue, https://github.com/Eastwu5788/Mask/issues
Platform: UNKNOWN
Requires-Python: >= 3.6
Requires-Dist: grpcio (>=1.38.0)
Requires-Dist: protobuf (==3.16.0)
Requires-Dist: grpcio-tools (>=1.38.0)
Requires-Dist: grpcio-reflection (>=1.38.0)
